{
	"jnList": [{
		"createTime": null,
		"timeYear": "2018-12-17",
		"fromcode": "",
		"timeStamp": null,
		"pageSign": "",
		"areaId": "57574685",
		"newCounts": "",
		"num": 2860,
		"timeStart": "",
		"timeEnd": "",
		"dur": "",
		"areaType": 0,
		"areaName": "道路一",
		"bearingCapacity": "",
		"longitude": "",
		"timeHour": "19",
		"latitude": "",
		"timeTemp": "2018-12-17 19:00:00",
		"trafficPer": 0
	}, {
		"createTime": null,
		"timeYear": "2018-12-17",
		"fromcode": "",
		"timeStamp": null,
		"pageSign": "",
		"areaId": "57574696",
		"areaName": "道路二",
		"newCounts": "",
		"num": 1908,
		"timeStart": "",
		"timeEnd": "",
		"dur": "",
		"areaType": 0,
		"bearingCapacity": "",
		"longitude": "",
		"timeHour": "19",
		"latitude": "",
		"timeTemp": "2018-12-17 19:00:00",
		"trafficPer": 0
	}, {
		"createTime": null,
		"timeYear": "2018-12-17",
		"fromcode": "",
		"timeStamp": null,
		"pageSign": "",
		"areaId": "57574666",
		"areaName": "道路三",
		"newCounts": "",
		"num": 1522,
		"timeStart": "",
		"timeEnd": "",
		"dur": "",
		"areaType": 0,
		"bearingCapacity": "",
		"longitude": "",
		"timeHour": "19",
		"latitude": "",
		"timeTemp": "2018-12-17 19:00:00",
		"trafficPer": 0
	}, {
		"createTime": null,
		"timeYear": "2018-12-17",
		"fromcode": "",
		"timeStamp": null,
		"pageSign": "",
		"areaId": "57574610",
		"areaName": "道路四",
		"newCounts": "",
		"num": 1966,
		"timeStart": "",
		"timeEnd": "",
		"dur": "",
		"areaType": 0,
		"bearingCapacity": "",
		"longitude": "",
		"timeHour": "19",
		"latitude": "",
		"timeTemp": "2018-12-17 19:00:00",
		"trafficPer": 0
	}, {
		"createTime": null,
		"timeYear": "2018-12-17",
		"fromcode": "",
		"timeStamp": null,
		"pageSign": "",
		"areaId": "57574622",
		"areaName": "道路五",
		"newCounts": "",
		"num": 832,
		"timeStart": "",
		"timeEnd": "",
		"dur": "",
		"areaType": 0,
		"bearingCapacity": "",
		"longitude": "",
		"timeHour": "19",
		"latitude": "",
		"timeTemp": "2018-12-17 19:00:00",
		"trafficPer": 0
	}, {
		"createTime": null,
		"timeYear": "2018-12-17",
		"fromcode": "",
		"timeStamp": null,
		"pageSign": "",
		"areaId": "57574668",
		"areaName": "道路六",
		"newCounts": "",
		"num": 2109,
		"timeStart": "",
		"timeEnd": "",
		"dur": "",
		"areaType": 0,
		"bearingCapacity": "",
		"longitude": "",
		"timeHour": "19",
		"latitude": "",
		"timeTemp": "2018-12-17 19:00:00",
		"trafficPer": 0
	}],
	"qnList": [],
	"jnName": "2018-12-17 19:00:00",
	"historyLydList": [{
		"createTime": null,
		"fromcode": "",
		"percent": "80.91",
		"timeStamp": null,
		"dataId": "",
		"areaId": "",
		"pageSign": "",
		"dataName": "绍兴",
		"dataType": 0,
		"timeStart": "",
		"timeEnd": "",
		"areaType": 0,
		"dataNum": 166822,
		"provId": ""
	}, {
		"createTime": null,
		"fromcode": "",
		"percent": "3.66",
		"timeStamp": null,
		"dataId": "",
		"areaId": "",
		"pageSign": "",
		"dataName": "杭州",
		"dataType": 0,
		"timeStart": "",
		"timeEnd": "",
		"areaType": 0,
		"dataNum": 7548,
		"provId": ""
	}, {
		"createTime": null,
		"fromcode": "",
		"percent": "1.64",
		"timeStamp": null,
		"dataId": "",
		"areaId": "",
		"pageSign": "",
		"dataName": "上海",
		"dataType": 0,
		"timeStart": "",
		"timeEnd": "",
		"areaType": 0,
		"dataNum": 3392,
		"provId": ""
	}, {
		"createTime": null,
		"fromcode": "",
		"percent": "1.45",
		"timeStamp": null,
		"dataId": "",
		"areaId": "",
		"pageSign": "",
		"dataName": "宁波",
		"dataType": 0,
		"timeStart": "",
		"timeEnd": "",
		"areaType": 0,
		"dataNum": 3001,
		"provId": ""
	}, {
		"createTime": null,
		"fromcode": "",
		"percent": "0.9",
		"timeStamp": null,
		"dataId": "",
		"areaId": "",
		"pageSign": "",
		"dataName": "温州",
		"dataType": 0,
		"timeStart": "",
		"timeEnd": "",
		"areaType": 0,
		"dataNum": 1863,
		"provId": ""
	}, {
		"createTime": null,
		"fromcode": "",
		"percent": "0.73",
		"timeStamp": null,
		"dataId": "",
		"areaId": "",
		"pageSign": "",
		"dataName": "金华",
		"dataType": 0,
		"timeStart": "",
		"timeEnd": "",
		"areaType": 0,
		"dataNum": 1520,
		"provId": ""
	}, {
		"createTime": null,
		"fromcode": "",
		"percent": "0.66",
		"timeStamp": null,
		"dataId": "",
		"areaId": "",
		"pageSign": "",
		"dataName": "嘉兴",
		"dataType": 0,
		"timeStart": "",
		"timeEnd": "",
		"areaType": 0,
		"dataNum": 1366,
		"provId": ""
	}, {
		"createTime": null,
		"fromcode": "",
		"percent": "0.53",
		"timeStamp": null,
		"dataId": "",
		"areaId": "",
		"pageSign": "",
		"dataName": "台州",
		"dataType": 0,
		"timeStart": "",
		"timeEnd": "",
		"areaType": 0,
		"dataNum": 1112,
		"provId": ""
	}, {
		"createTime": null,
		"fromcode": "",
		"percent": "0.41",
		"timeStamp": null,
		"dataId": "",
		"areaId": "",
		"pageSign": "",
		"dataName": "北京",
		"dataType": 0,
		"timeStart": "",
		"timeEnd": "",
		"areaType": 0,
		"dataNum": 861,
		"provId": ""
	}, {
		"createTime": null,
		"fromcode": "",
		"percent": "0.33",
		"timeStamp": null,
		"dataId": "",
		"areaId": "",
		"pageSign": "",
		"dataName": "苏州",
		"dataType": 0,
		"timeStart": "",
		"timeEnd": "",
		"areaType": 0,
		"dataNum": 688,
		"provId": ""
	}],
	"qnName": "2017-12-17 19:00:00",
	"hisGender": [{
		"createTime": null,
		"fromcode": "",
		"timeStamp": null,
		"genderId": "1",
		"areaId": "",
		"pageSign": "",
		"newCounts": 0,
		"num": 93159,
		"timeStart": "",
		"timeEnd": "",
		"areaType": 0,
		"genderName": "",
		"timeTemp": ""
	}, {
		"createTime": null,
		"fromcode": "",
		"timeStamp": null,
		"genderId": "2",
		"areaId": "",
		"pageSign": "",
		"newCounts": 0,
		"num": 64673,
		"timeStart": "",
		"timeEnd": "",
		"areaType": 0,
		"genderName": "",
		"timeTemp": ""
	}],
	"hisAge": [{
		"createTime": null,
		"ageName": "18岁以下",
		"fromcode": "",
		"timeStamp": null,
		"ageC": "",
		"ageD": "",
		"ageE": "",
		"pageSign": "",
		"ageA": "",
		"areaId": "",
		"ageB": "",
		"num": 443,
		"timeStart": "",
		"timeEnd": "",
		"areaType": 0,
		"ageId": "1"
	}, {
		"createTime": null,
		"ageName": "61岁以上",
		"fromcode": "",
		"timeStamp": null,
		"ageC": "",
		"ageD": "",
		"ageE": "",
		"pageSign": "",
		"ageA": "",
		"areaId": "",
		"ageB": "",
		"num": 13677,
		"timeStart": "",
		"timeEnd": "",
		"areaType": 0,
		"ageId": "4"
	}, {
		"createTime": null,
		"ageName": "18岁-35岁",
		"fromcode": "",
		"timeStamp": null,
		"ageC": "",
		"ageD": "",
		"ageE": "",
		"pageSign": "",
		"ageA": "",
		"areaId": "",
		"ageB": "",
		"num": 71880,
		"timeStart": "",
		"timeEnd": "",
		"areaType": 0,
		"ageId": "2"
	}, {
		"createTime": null,
		"ageName": "36岁-60岁",
		"fromcode": "",
		"timeStamp": null,
		"ageC": "",
		"ageD": "",
		"ageE": "",
		"pageSign": "",
		"ageA": "",
		"areaId": "",
		"ageB": "",
		"num": 95276,
		"timeStart": "",
		"timeEnd": "",
		"areaType": 0,
		"ageId": "3"
	}],
	"hisLyd": [{
		"createTime": null,
		"fromcode": "",
		"percent": "",
		"timeStamp": null,
		"dataId": "",
		"areaId": "",
		"pageSign": "",
		"dataName": "",
		"dataType": 2,
		"timeStart": "",
		"timeEnd": "",
		"areaType": 0,
		"dataNum": 257,
		"provId": ""
	}, {
		"createTime": null,
		"fromcode": "",
		"percent": "",
		"timeStamp": null,
		"dataId": "",
		"areaId": "",
		"pageSign": "",
		"dataName": "",
		"dataType": 0,
		"timeStart": "",
		"timeEnd": "",
		"areaType": 0,
		"dataNum": 21228,
		"provId": ""
	}, {
		"createTime": null,
		"fromcode": "",
		"percent": "",
		"timeStamp": null,
		"dataId": "",
		"areaId": "",
		"pageSign": "",
		"dataName": "",
		"dataType": 1,
		"timeStart": "",
		"timeEnd": "",
		"areaType": 0,
		"dataNum": 206164,
		"provId": ""
	}],
	"hisZlsj": {
		"createTime": null,
		"sjE": "22612",
		"sjD": "7731",
		"fromcode": "",
		"sjC": "12421",
		"timeStamp": null,
		"sjB": "24871",
		"sjA": "143245",
		"zlsjId": "",
		"zlsjName": "",
		"areaId": "",
		"pageSign": "",
		"num": 0,
		"timeEnd": "",
		"timeStart": "",
		"areaType": 0
	},
	"hisSnLyd": [{
		"createTime": null,
		"fromcode": "",
		"percent": "",
		"timeStamp": null,
		"dataId": "",
		"areaId": "",
		"pageSign": "",
		"dataName": "",
		"dataType": 2,
		"timeStart": "",
		"timeEnd": "",
		"areaType": 0,
		"dataNum": 1,
		"provId": ""
	}, {
		"createTime": null,
		"fromcode": "",
		"percent": "",
		"timeStamp": null,
		"dataId": "",
		"areaId": "",
		"pageSign": "",
		"dataName": "",
		"dataType": 1,
		"timeStart": "",
		"timeEnd": "",
		"areaType": 0,
		"dataNum": 184936,
		"provId": ""
	}]
}